data/50-wooting.rules
data/wooting-mouse@.service
wooting_mouse.py
wooting_mouse-1.0.2.dist-info/METADATA
wooting_mouse-1.0.2.dist-info/WHEEL
wooting_mouse-1.0.2.dist-info/entry_points.txt
wooting_mouse-1.0.2.dist-info/licenses/LICENSE
wooting_mouse-1.0.2.dist-info/RECORD
