Metadata-Version: 2.4
Name: wooting-mouse
Version: 1.0.2
Summary: Use Wooting Gamepad as Virtual Mouse
License: GPL-3.0
License-File: LICENSE
Author: Dick Marinus
Requires-Python: >=3.13,<4.0
Classifier: License :: OSI Approved :: GNU General Public License v3 (GPLv3)
Classifier: Programming Language :: Python :: 3
Classifier: Programming Language :: Python :: 3.13
Classifier: Programming Language :: Python :: 3.14
Requires-Dist: evdev (>=1.6.1,<2.0.0)
Requires-Dist: hsluv (>=5.0.3,<6.0.0)
Requires-Dist: libwootility[linux] (>=1.0.0)
Requires-Dist: pyudev (>=0.24.1,<0.25.0)
